{
  "hero": "assets/6067390.webp",
  "photos": [
    {
      "image": "assets/6067392.webp",
      "alt": "Evento 1"
    },
    {
      "image": "assets/6067401.webp",
      "alt": "Evento 2"
    },
    {
      "image": "assets/6067427.webp",
      "alt": "Evento 3"
    },
    {
      "image": "assets/6067440.webp",
      "alt": "Evento 4"
    },
    {
      "image": "assets/6067471.webp",
      "alt": "Evento 5"
    },
    {
      "image": "assets/6067483.webp",
      "alt": "Evento 6"
    }
  ]
}
